wapttools/__init__.py
wapttools/__main__.py
wapttools/annotate.py
wapttools/build.py
wapttools/check.py
wapttools/commands.py
wapttools/config.py
wapttools/control.py
wapttools/create.py
wapttools/download.py
wapttools/hash.py
wapttools/log.py
wapttools/release.py
wapttools/update.py
wapttools/upload.py
wapttools/validate.py
wapttools/vers.py
wapttools/version.py
wapttools/wapttools.py
wapttools/data/__init__.py
wapttools/data/chat_message.json
wapttools/data/default_icon.png
wapttools/data/editorconfig.ini
wapttools/data/flake8.txt
wapttools/data/pre-commit-config.yaml
wapttools/data/setup.tmpl
wapttools/data/version-check.json
wapttools/data/vscode_extensions.json
wapttools/data/vscode_launch.json
wapttools/data/vscode_settings.json
wapttools/data/wapt_control.txt
wapt_tools-2.0.0.dist-info/LICENSE
wapt_tools-2.0.0.dist-info/METADATA
wapt_tools-2.0.0.dist-info/WHEEL
wapt_tools-2.0.0.dist-info/entry_points.txt
wapt_tools-2.0.0.dist-info/top_level.txt
wapt_tools-2.0.0.dist-info/RECORD
