Metadata-Version: 2.1
Name: wapt-tools
Version: 2.0.0
Summary: "WAPT packaging utilities."
Home-page: https://github.com/lrobinot/wapt-tools
Author: Ludovic ROBINOT
Author-email: lrobinot@gmail.com
License: Apache 2.0
Platform: UNKNOWN
Requires-Python: >=3.8.17
Requires-Dist: anybadge (==1.14.0)
Requires-Dist: beautifulsoup4 (==4.11.2)
Requires-Dist: flake8 (==6.1.0)
Requires-Dist: packaging (==23.2)
Requires-Dist: pefile (==2023.2.7)
Requires-Dist: plumbum (==1.8.2)
Requires-Dist: pre-commit (==3.5.0)
Requires-Dist: python-gitlab (==3.15.0)
